{"fps":30,"backgroundMusic":"https://musicfile.api.box/ZjQwYTFmZjItOTdjYS00NTFlLWFmNWQtYjE0NDAzZDE2ZGVk.mp3","backgroundMusicVolume":0.15,"watermark":{"text":"Rafelune","position":"top-left","scale":0.8},"shorts":[{"title":"Forest Glow","startInSeconds":30,"endInSeconds":60,"description":"Moonlit clearing with glowing fireflies and ancient trees."},{"title":"Cabin Warmth","startInSeconds":150,"endInSeconds":180,"description":"Cozy cabin interior with a warm fireplace and scattered books."}],"scenes":[{"assets":["https://o.uguu.se/DDMUjrLr.jpg"],"durationInSeconds":20,"kenBurns":{"startScale":1.15,"endScale":1.05,"easing":"easeOut"},"particles":{"type":"fireflies","count":30,"showAt":0,"hideAt":20},"visualizer":{"type":"dots","color":"#ffffff","position":"bottom"},"transitionAfter":"fade","transitionDuration":2},{"assets":["https://n.uguu.se/BcZOxcit.jpg"],"durationInSeconds":20,"kenBurns":{"startScale":1.15,"endScale":1.05,"easing":"easeOut"},"particles":{"type":"fireflies","count":30,"showAt":0,"hideAt":20},"visualizer":{"type":"dots","color":"#ffffff","position":"bottom"},"transitionAfter":"fade","transitionDuration":2},{"assets":["https://h.uguu.se/OXCynCbG.jpg"],"durationInSeconds":20,"kenBurns":{"startScale":1.15,"endScale":1.05,"easing":"easeOut"},"particles":{"type":"fireflies","count":30,"showAt":0,"hideAt":20},"visualizer":{"type":"dots","color":"#ffffff","position":"bottom"},"transitionAfter":"fade","transitionDuration":2},{"assets":["https://d.uguu.se/qGLgrORS.jpg"],"durationInSeconds":20,"kenBurns":{"startScale":1.15,"endScale":1.05,"easing":"easeOut"},"particles":{"type":"fireflies","count":30,"showAt":0,"hideAt":20},"visualizer":{"type":"dots","color":"#ffffff","position":"bottom"},"transitionAfter":"fade","transitionDuration":2},{"assets":["https://n.uguu.se/bxdyxlUF.jpg"],"durationInSeconds":20,"kenBurns":{"startScale":1.15,"endScale":1.05,"easing":"easeOut"},"particles":{"type":"fireflies","count":30,"showAt":0,"hideAt":20},"visualizer":{"type":"dots","color":"#ffffff","position":"bottom"},"transitionAfter":"fade","transitionDuration":2},{"assets":["https://d.uguu.se/hOjHNPeE.jpg"],"durationInSeconds":20,"kenBurns":{"startScale":1.15,"endScale":1.05,"easing":"easeOut"},"particles":{"type":"fireflies","count":30,"showAt":0,"hideAt":20},"visualizer":{"type":"dots","color":"#ffffff","position":"bottom"},"transitionAfter":"fade","transitionDuration":2},{"assets":["https://o.uguu.se/dCKgwPpd.jpg"],"durationInSeconds":20,"kenBurns":{"startScale":1.15,"endScale":1.05,"easing":"easeOut"},"particles":{"type":"fireflies","count":30,"showAt":0,"hideAt":20},"visualizer":{"type":"dots","color":"#ffffff","position":"bottom"},"transitionAfter":"fade","transitionDuration":2},{"assets":["https://h.uguu.se/HHuSyNKQ.jpg"],"durationInSeconds":20,"kenBurns":{"startScale":1.15,"endScale":1.05,"easing":"easeOut"},"particles":{"type":"fireflies","count":30,"showAt":0,"hideAt":20},"visualizer":{"type":"dots","color":"#ffffff","position":"bottom"},"transitionAfter":"fade","transitionDuration":2},{"assets":["https://h.uguu.se/GLsURgYw.jpg"],"durationInSeconds":20,"kenBurns":{"startScale":1.15,"endScale":1.05,"easing":"easeOut"},"particles":{"type":"fireflies","count":30,"showAt":0,"hideAt":20},"visualizer":{"type":"dots","color":"#ffffff","position":"bottom"},"transitionAfter":"fade","transitionDuration":2},{"assets":["https://n.uguu.se/XThARqXM.jpg"],"durationInSeconds":20,"kenBurns":{"startScale":1.15,"endScale":1.05,"easing":"easeOut"},"particles":{"type":"fireflies","count":30,"showAt":0,"hideAt":20},"visualizer":{"type":"dots","color":"#ffffff","position":"bottom"},"transitionAfter":"fade","transitionDuration":2},{"assets":["https://d.uguu.se/CsqCHeDg.jpg"],"durationInSeconds":20,"kenBurns":{"startScale":1.15,"endScale":1.05,"easing":"easeOut"},"particles":{"type":"fireflies","count":30,"showAt":0,"hideAt":20},"visualizer":{"type":"dots","color":"#ffffff","position":"bottom"},"transitionAfter":"fade","transitionDuration":2},{"assets":["https://h.uguu.se/tCPcumSD.jpg"],"durationInSeconds":20,"kenBurns":{"startScale":1.15,"endScale":1.05,"easing":"easeOut"},"particles":{"type":"fireflies","count":30,"showAt":0,"hideAt":20},"visualizer":{"type":"dots","color":"#ffffff","position":"bottom"},"transitionAfter":"fade","transitionDuration":2},{"assets":["https://h.uguu.se/MjqACdBr.jpg"],"durationInSeconds":20,"kenBurns":{"startScale":1.15,"endScale":1.05,"easing":"easeOut"},"particles":{"type":"fireflies","count":30,"showAt":0,"hideAt":20},"visualizer":{"type":"dots","color":"#ffffff","position":"bottom"},"transitionAfter":"fade","transitionDuration":2},{"assets":["https://d.uguu.se/oLXlgHEx.jpg"],"durationInSeconds":20,"kenBurns":{"startScale":1.15,"endScale":1.05,"easing":"easeOut"},"particles":{"type":"fireflies","count":30,"showAt":0,"hideAt":20},"visualizer":{"type":"dots","color":"#ffffff","position":"bottom"},"transitionAfter":"fade","transitionDuration":2},{"assets":["https://n.uguu.se/XpNZtuwM.jpg"],"durationInSeconds":20,"kenBurns":{"startScale":1.15,"endScale":1.05,"easing":"easeOut"},"particles":{"type":"fireflies","count":30,"showAt":0,"hideAt":20},"visualizer":{"type":"dots","color":"#ffffff","position":"bottom"},"transitionAfter":"fade","transitionDuration":2}],"data":{"taskId":"e41f23dddecb72708b61da46926d39c2"}}